<?xml version="1.0"?>
<root>

    <!-- configurations -->

    <item>
        <name>⌘: Switch CapsLock And Esc</name>
        <item>
            <name style="important">!Important Steps:</name>
            <appendix>1. Install Seil and Launch it.</appendix>
            <appendix>2. Change Caps Lock's keycode to 80.</appendix>
            <appendix>3. open "System Preferences > Keyboard > Modifier Keys..." and change caps lock configuration to "No Action".</appendix>
            <appendix>Refer to: https://pqrs.org/osx/karabiner/seil.html</appendix>
            <identifier>private.CapslockEscSwitcher</identifier>
            <autogen>
                --KeyToKey--
                KeyCode::F19, 
                KeyCode::ESCAPE
            </autogen>
        </item>
    </item>

</root>